MANIFEST.in
README.md
requirements.txt
setup.py
garner/__init__.py
garner/config.py
garner.egg-info/PKG-INFO
garner.egg-info/SOURCES.txt
garner.egg-info/dependency_links.txt
garner.egg-info/not-zip-safe
garner.egg-info/requires.txt
garner.egg-info/top_level.txt
garner/api/__init__.py
garner/api/api.py
garner/api/web_socket.py
garner/authentication/__init__.py
garner/authentication/authentication.py
garner/authentication/aws_srp.py
garner/authentication/exceptions.py
garner/datatypes/__init__.py
garner/datatypes/boolean.py
garner/datatypes/double_gif.py
garner/datatypes/double_image.py
garner/datatypes/gif.py
garner/datatypes/image.py
garner/datatypes/text.py
garner/datatypes/.ipynb_checkpoints/image-checkpoint.py
garner/pool/__init__.py
garner/pool/pool.py
garner/storage/__init__.py
garner/storage/storage.py