Metadata-Version: 2.1
Name: garner
Version: 0.0.5
Summary: A library for interacting with the Garner API.
Home-page: https://github.com/kipgparker/Garner-python
Author: kip parker
Author-email: kip@garner.app
License: MIT license
Platform: UNKNOWN
Classifier: Development Status :: 3 - Alpha
Classifier: Intended Audience :: Developers
Classifier: Intended Audience :: Science/Research
Classifier: License :: OSI Approved :: MIT License
Classifier: Natural Language :: English
Classifier: Programming Language :: Python :: 3.7
Classifier: Topic :: Scientific/Engineering :: Artificial Intelligence
Classifier: Topic :: Software Development :: Libraries :: Python Modules
